gaelic.py
setup.py
Gaelic.egg-info/PKG-INFO
Gaelic.egg-info/SOURCES.txt
Gaelic.egg-info/dependency_links.txt
Gaelic.egg-info/entry_points.txt
Gaelic.egg-info/requires.txt
Gaelic.egg-info/top_level.txt