Metadata-Version: 1.0
Name: Gaelic
Version: 1.0
Summary: Google App Engine package installer (pip bridge)
Home-page: http://bitbucket.org/jonparrott/gaelic
Author: Jon Wayne Parrott
Author-email: jjramone13@gmail.com
License: UNKNOWN
Platform: UNKNOWN
